AUTHORS
CHANGELOG
LICENSE
MANIFEST.in
README.rst
entrypoint.py
setup.cfg
setup.py
inspire_mitmproxy/__init__.py
inspire_mitmproxy/dispatcher.py
inspire_mitmproxy/errors.py
inspire_mitmproxy/http.py
inspire_mitmproxy/interaction.py
inspire_mitmproxy/service_list.py
inspire_mitmproxy.egg-info/PKG-INFO
inspire_mitmproxy.egg-info/SOURCES.txt
inspire_mitmproxy.egg-info/dependency_links.txt
inspire_mitmproxy.egg-info/not-zip-safe
inspire_mitmproxy.egg-info/requires.txt
inspire_mitmproxy.egg-info/top_level.txt
inspire_mitmproxy/services/__init__.py
inspire_mitmproxy/services/base_service.py
inspire_mitmproxy/services/management_service.py
inspire_mitmproxy/services/whitelist_service.py
scripts/vcr_convert.py