Metadata-Version: 2.1
Name: inspire-mitmproxy
Version: 0.13.3
Summary: INSPIRE MITMProxy for E2E Tests.
Home-page: https://github.com/inspirehep/inspire-mitmproxy
Author: CERN
Author-email: admin@inspirehep.net
License: GPLv3
Platform: any
Classifier: Intended Audience :: Developers
Classifier: Environment :: Console
Classifier: License :: OSI Approved :: BSD License
Classifier: Operating System :: OS Independent
Classifier: Topic :: Internet :: WWW/HTTP
Classifier: Topic :: Software Development :: Libraries :: Application Frameworks
Classifier: Topic :: Software Development :: Libraries :: Python Modules
Classifier: Programming Language :: Python
Classifier: Programming Language :: Python :: 3
Classifier: Programming Language :: Python :: 3.6
Provides-Extra: tests
Provides-Extra: docs
Provides-Extra: all
